Workbook

Sheet Inversion Inicial
A1: Concepto | B1: Valor (€)
A2: Selección del Account Manager | B2: 0
A3: Lead Magnet + diseño de materiales y traducción | B3: 1400
A4: Fondo de maniobra | B4: 20000
A5: Subtotal | B5: =B2+B3+B4 -> 21400
A6: Contingencia 10% | B6: =0.1*B5 -> 2140
A7: Total inversión inicial | B7: =B5+B6 -> 23540

Sheet Costes Fijos
A1: Concepto | B1: Valor anual (€)
A2: Hosting/Web | B2: 0
A3: KAM | B3: 40000
A4: Total Costes Fijos | B4: =B2+B3 -> 40000

Sheet Escenarios
A1: Escenarios | B1: Basic | C1: Lite | D1: Premium | E1: COGS
A2: Escenario Conservador | B2: 0.6 | C2: 0.3 | D2: 0.1 | E2: 0.75
A3: Escenario Realista: | B3: 0.4 | C3: 0.4 | D3: 0.2 | E3: 0.7
A4: Escenario Optimista | B4: 0.2 | C4: 0.4 | D4: 0.4 | E4: 0.65

Sheet Desglose por escenarios
A1: Concepto | B1: Cifra (€)
A2: Precio basic | B2: 10300
A3: Precio lite | B3: 13900
A4: Precio premium | B4: 17440
A5: Target de clientes primer año | B5: 8
A6: Inversión Inicial | B6: ='Inversion Inicial'!B7 -> 23540
A7: Costes Fijos Anuales | B7: ='Costes Fijos'!B4 -> 40000

Sheet Proyección por Escenarios
A1: Escenarios | B1: Pack basic | C1: Pack lite | D1: Pack premium | E1: Precio ponderdo mes por cliente | F1: Ingreso Total Mes | G1: Ingreso Total Año | H1: COGS | I1: Margen Bruto | J1: EBIT | K1: Impuesto | L1: Resultado Neto | M1: ROI | N1: Payback Meses | O1: Clientes BE operativo Mes | P1: Clientes BE Total Mes
A2: Conservador | B2: ='Desglose por escenarios'!B2*0.6 -> 6180 | C2: ='Desglose por escenarios'!B3*0.3 -> 4170 | D2: ='Desglose por escenarios'!B4*0.1 -> 1744 | E2: =B2+C2+D2 -> 12094 | F2: =E2*'Desglose por escenarios'!B5 -> 96752 | G2: =F2*12 -> 1161024 | H2: =Tabla1[[#This Row],[Ingreso Total Año]]*Escenarios!E2 -> 870768 | I2: =Tabla1[[#This Row],[Ingreso Total Año]]-Tabla1[[#This Row],[COGS]] -> 290256 | J2: =Tabla1[[#This Row],[Margen Bruto]]-'Desglose por escenarios'!B$7 -> 250256 | K2: =0.25*Tabla1[[#This Row],[EBIT]] -> 62564 | L2: =Tabla1[[#This Row],[EBIT]]-Tabla1[[#This Row],[Impuesto]] -> 187692 | M2: =Tabla1[[#This Row],[Resultado Neto]]/'Desglose por escenarios'!B$6 -> 7.973322 | N2: =ROUND(('Desglose por escenarios'!B$6/Tabla1[[#This Row],[Resultado Neto]])*12,0) -> 2 | O2: ='Costes Fijos'!B$4/((Tabla1[[#This Row],[Precio ponderdo mes por cliente]]*12)*(1-Escenarios!E2)) -> 1.1024751 | P2: =('Desglose por escenarios'!B$7+'Desglose por escenarios'!B$6)/((Tabla1[[#This Row],[Precio ponderdo mes por cliente]]*12)*(1-Escenarios!E2)) -> 1.7512816
A3: Realista | B3: ='Desglose por escenarios'!B2*0.4 -> 4120 | C3: ='Desglose por escenarios'!B3*0.4 -> 5560 | D3: ='Desglose por escenarios'!B4*0.2 -> 3488 | E3: =B3+C3+D3 -> 13168 | F3: =E3*'Desglose por escenarios'!B5 -> 105344 | G3: =F3*12 -> 1264128 | H3: =Tabla1[[#This Row],[Ingreso Total Año]]*Escenarios!E3 -> 884889.6 | I3: =Tabla1[[#This Row],[Ingreso Total Año]]-Tabla1[[#This Row],[COGS]] -> 379238.4 | J3: =Tabla1[[#This Row],[Margen Bruto]]-'Desglose por escenarios'!B$7 -> 339238.4 | K3: =0.25*Tabla1[[#This Row],[EBIT]] -> 84809.6 | L3: =Tabla1[[#This Row],[EBIT]]-Tabla1[[#This Row],[Impuesto]] -> 254428.8 | M3: =Tabla1[[#This Row],[Resultado Neto]]/'Desglose por escenarios'!B$6 -> 10.80836 | N3: =ROUND(('Desglose por escenarios'!B$6/Tabla1[[#This Row],[Resultado Neto]])*12,0) -> 1 | O3: ='Costes Fijos'!B$4/((Tabla1[[#This Row],[Precio ponderdo mes por cliente]]*12)*(1-Escenarios!E3)) -> 0.84379641 | P3: =('Desglose por escenarios'!B$7+'Desglose por escenarios'!B$6)/((Tabla1[[#This Row],[Precio ponderdo mes por cliente]]*12)*(1-Escenarios!E3)) -> 1.3403706
A4: Optimista | B4: ='Desglose por escenarios'!B2*0.2 -> 2060 | C4: ='Desglose por escenarios'!B3*0.4 -> 5560 | D4: ='Desglose por escenarios'!B4*0.4 -> 6976 | E4: =B4+C4+D4 -> 14596 | F4: =E4*'Desglose por escenarios'!B5 -> 116768 | G4: =F4*12 -> 1401216 | H4: =Tabla1[[#This Row],[Ingreso Total Año]]*Escenarios!E4 -> 910790.4 | I4: =Tabla1[[#This Row],[Ingreso Total Año]]-Tabla1[[#This Row],[COGS]] -> 490425.6 | J4: =Tabla1[[#This Row],[Margen Bruto]]-'Desglose por escenarios'!B$7 -> 450425.6 | K4: =0.25*Tabla1[[#This Row],[EBIT]] -> 112606.4 | L4: =Tabla1[[#This Row],[EBIT]]-Tabla1[[#This Row],[Impuesto]] -> 337819.2 | M4: =Tabla1[[#This Row],[Resultado Neto]]/'Desglose por escenarios'!B$6 -> 14.350858 | N4: =ROUND(('Desglose por escenarios'!B$6/Tabla1[[#This Row],[Resultado Neto]])*12,0) -> 1 | O4: ='Costes Fijos'!B$4/((Tabla1[[#This Row],[Precio ponderdo mes por cliente]]*12)*(1-Escenarios!E4)) -> 0.65249449 | P4: =('Desglose por escenarios'!B$7+'Desglose por escenarios'!B$6)/((Tabla1[[#This Row],[Precio ponderdo mes por cliente]]*12)*(1-Escenarios!E4)) -> 1.0364875

Sheet Suma de Ingresos Total Años 
A1: Etiquetas de columna
A2: Conservador | D2: Optimista | G2: Realista | J2: Total Suma de Ingreso Total Año | K2: Total Suma de Margen Bruto | L2: Total Suma de Resultado Neto
A3: Suma de Ingreso Total Año | B3: Suma de Margen Bruto | C3: Suma de Resultado Neto | D3: Suma de Ingreso Total Año | E3: Suma de Margen Bruto | F3: Suma de Resultado Neto | G3: Suma de Ingreso Total Año | H3: Suma de Margen Bruto | I3: Suma de Resultado Neto
A4: 435384 | B4: 108846 | C4: 51544.5 | D4: 525456 | E4: 183909.6 | F4: 107842.2 | G4: 474048 | H4: 142214.4 | I4: 76570.8 | J4: 1434888 | K4: 434970 | L4: 235957.5

Sheet ROI
A1: Etiquetas de fila | B1: Suma de ROI
A2: 51544.5 | B2: 2.1794715
A3: Conservador | B3: 2.1794715
A4: 76570.8 | B4: 3.237666
A5: Realista | B5: 3.237666
A6: 107842.2 | B6: 4.5599239
A7: Optimista | B7: 4.5599239
A8: Total general | B8: 9.9770613

Sheet Proyeccion 12 meses
A1: Mes | B1: Clientes Acumulativos | C1: Ingresos (€) Cuota mensual cliente | D1: Costes Fijos (€) | E1: Costes Variables (€) | F1: Beneficio (€) | G1: Beneficio Acumulado (€)
A2: 1 | B2: 0 | D2: ='Desglose por escenarios'!B$7/12 -> 3333.3333 | E2: =C2*0.75 -> 0 | F2: =C2-D2-E2 -> -3333.3333 | G2: =F2 -> -3333.3333
A3: 2 | B3: 0 | D3: ='Desglose por escenarios'!B$7/12 -> 3333.3333 | E3: =C3*0.75 -> 0 | F3: =C3-D3-E3 -> -3333.3333 | G3: =F3+G2 -> -6666.6667
A4: 3 | B4: 1 | C4: ='Proyección por Escenarios'!E$2*B4 -> 12094 | D4: ='Desglose por escenarios'!B$7/12 -> 3333.3333 | E4: =C4*0.75 -> 9070.5 | F4: =C4-D4-E4 -> -309.83333 | G4: =G3+F4 -> -6976.5
A5: 4 | B5: 1 | C5: ='Proyección por Escenarios'!E$2*B5 -> 12094 | D5: ='Desglose por escenarios'!B$7/12 -> 3333.3333 | E5: =C5*0.75 -> 9070.5 | F5: =C5-D5-E5 -> -309.83333 | G5: =F4+G4 -> -7286.3333
A6: 5 | B6: 2 | C6: ='Proyección por Escenarios'!E$2*B6 -> 24188 | D6: ='Desglose por escenarios'!B$7/12 -> 3333.3333 | E6: =C6*0.75 -> 18141 | F6: =C6-D6-E6 -> 2713.6667 | G6: =F5+G5 -> -7596.1667
A7: 6 | B7: 2 | C7: ='Proyección por Escenarios'!E$2*B7 -> 24188 | D7: ='Desglose por escenarios'!B$7/12 -> 3333.3333 | E7: =C7*0.75 -> 18141 | F7: =C7-D7-E7 -> 2713.6667 | G7: =F6+G6 -> -4882.5
A8: 7 | B8: 3 | C8: ='Proyección por Escenarios'!E$2*B8 -> 36282 | D8: ='Desglose por escenarios'!B$7/12 -> 3333.3333 | E8: =C8*0.75 -> 27211.5 | F8: =C8-D8-E8 -> 5737.1667 | G8: =F7+G7 -> -2168.8333
A9: 8 | B9: 3 | C9: ='Proyección por Escenarios'!E$2*B9 -> 36282 | D9: ='Desglose por escenarios'!B$7/12 -> 3333.3333 | E9: =C9*0.75 -> 27211.5 | F9: =C9-D9-E9 -> 5737.1667 | G9: =F8+G8 -> 3568.3333
A10: 9 | B10: 3 | C10: ='Proyección por Escenarios'!E$2*B10 -> 36282 | D10: ='Desglose por escenarios'!B$7/12 -> 3333.3333 | E10: =C10*0.75 -> 27211.5 | F10: =C10-D10-E10 -> 5737.1667 | G10: =F9+G9 -> 9305.5
A11: 10 | B11: 3 | C11: ='Proyección por Escenarios'!E$2*B11 -> 36282 | D11: ='Desglose por escenarios'!B$7/12 -> 3333.3333 | E11: =C11*0.75 -> 27211.5 | F11: =C11-D11-E11 -> 5737.1667 | G11: =F10+G10 -> 15042.667
A12: 11 | B12: 4 | C12: ='Proyección por Escenarios'!E$2*B12 -> 48376 | D12: ='Desglose por escenarios'!B$7/12 -> 3333.3333 | E12: =C12*0.75 -> 36282 | F12: =C12-D12-E12 -> 8760.6667 | G12: =F11+G11 -> 20779.833
A13: 12 | B13: 4 | C13: ='Proyección por Escenarios'!E$2*B13 -> 48376 | D13: ='Desglose por escenarios'!B$7/12 -> 3333.3333 | E13: =C13*0.75 -> 36282 | F13: =C13-D13-E13 -> 8760.6667 | G13: =F12+G12 -> 29540.5
